Shift_Register/rightshiftreg/rightshiftreg.v
module rightshiftreg (clk,rst,in,a);

//input wire [3:0] in;
input wire clk;
input wire rst;
input wire in;

output reg  [3:0] a;

always @(posedge clk) begin
    if(rst)

    a=4'b0000;

    else begin

    a ={in,a[3:1]};


    end
    
end
    
 endmodule

Shift_Register/rightshiftreg/rightshiftreg_tb.v
module rightshiftreg_tb;

   // reg [3:0] in_data;
    reg clk;
    reg rst;
    reg in;
    wire [3:0] a_tb;

    always #5 clk = ~clk;

    initial begin
        clk = 0;
        rst = 1;
        #10;
        rst = 0;
        in =1 ;
        #10;
        in = 0;
        #10;
        in = 0;
        #10;
        in = 0;
        #10;

        $finish;
    end

    rightshiftreg u_shiftut (
        .clk(clk),
        .rst(rst),
        .in(in),
        .a(a_tb)
    );

    initial begin
        $dumpfile("rightshiftreg.vcd");
        $dumpvars(0, rightshiftreg_tb);
    end
endmodule

Shift_Register/rightshiftreg/rightshiftreg.vcd
$date
	Wed Aug  9 12:34:14 2023
$end
$version
	Icarus Verilog
$end
$timescale
	1s
$end
$scope module rightshiftreg_tb $end
$var wire 4 ! a_tb [3:0] $end
$var reg 1 " clk $end
$var reg 1 # in $end
$var reg 1 $ rst $end
$scope module u_shiftut $end
$var wire 1 " clk $end
$var wire 1 # in $end
$var wire 1 $ rst $end
$var reg 4 % a [3:0] $end
$upscope $end
$upscope $end
$enddefinitions $end
#0
$dumpvars
bx %
1$
x#
0"
bx !
$end
#5
b0 !
b0 %
1"
#10
0"
1#
0$
#15
b1000 !
b1000 %
1"
#20
0"
0#
#25
b100 !
b100 %
1"
#30
0"
#35
b10 !
b10 %
1"
#40
0"
#45
b1 !
b1 %
1"
