FA/fa.v
module fa (A,B,Cin,sum,carry);
    input wire A;
    input wire B;
    input wire Cin;
    output wire sum;
    output wire carry;

    wire s0;
    wire c1;
    wire c0;

    assign s0 = A^B;
    assign sum = s0^Cin;

    assign c0 = A&B;
    assign c1 = s0&Cin;
    assign carry = c0|c1;

endmodule

FA/fa_tb.v
`timescale 1ns/1ps
module fa_tb();

    reg a_tb;
    reg b_tb;
    reg cin_tb;
    wire sum_tb; 
    wire carry_tb;

    initial begin
        a_tb=0; b_tb=0; cin_tb=0;
        #1;
        a_tb=0; b_tb=0; cin_tb=1;
        #1;
        a_tb=0; b_tb=1; cin_tb=0;
        #1;
        a_tb=0; b_tb=1; cin_tb=1;
        #1;
        a_tb=1; b_tb=0; cin_tb=0;
        #1;
        a_tb=1; b_tb=0; cin_tb=1;
        #1;
        a_tb=1; b_tb=1; cin_tb=0;
        #1;
        a_tb=1; b_tb=1; cin_tb=1;


        $display ("sum_tb value is %d",sum_tb);
        $display ("carry_tb value is %d",carry_tb);
        #1;
    end

    fa u_fa0
    (
        .A(a_tb),
        .B(b_tb),
        .Cin(cin_tb),
        .sum(sum_tb),
        .carry(carry_tb)
    );

    initial begin
        $dumpfile ("fa.vcd");
        $dumpvars (0, fa_tb);
    end
endmodule

FA/fa.vcd
$date
	Fri Aug  4 14:24:32 2023
$end
$version
	Icarus Verilog
$end
$timescale
	1ps
$end
$scope module fa_tb $end
$var wire 1 ! sum_tb $end
$var wire 1 " carry_tb $end
$var reg 1 # a_tb $end
$var reg 1 $ b_tb $end
$var reg 1 % cin_tb $end
$scope module u_fa0 $end
$var wire 1 # A $end
$var wire 1 $ B $end
$var wire 1 % Cin $end
$var wire 1 & c0 $end
$var wire 1 ' c1 $end
$var wire 1 " carry $end
$var wire 1 ( s0 $end
$var wire 1 ! sum $end
$upscope $end
$upscope $end
$enddefinitions $end
#0
$dumpvars
0(
0'
0&
0%
0$
0#
0"
0!
$end
#1000
1!
1%
#2000
1(
0%
1$
#3000
1"
0!
1'
1%
#4000
0"
1!
0'
0%
0$
1#
#5000
1"
0!
1'
1%
#6000
0'
0(
1&
0%
1$
#7000
1!
1%
